README.rst
setup.py
mpack/__init__.py
mpack/_cmpack.pxd
mpack/_mpack.c
mpack/_mpack.pyx
mpack/asyncio.py
mpack.egg-info/PKG-INFO
mpack.egg-info/SOURCES.txt
mpack.egg-info/dependency_links.txt
mpack.egg-info/requires.txt
mpack.egg-info/top_level.txt
mpack/mpack-src/src/conv.c
mpack/mpack-src/src/conv.h
mpack/mpack-src/src/core.c
mpack/mpack-src/src/core.h
mpack/mpack-src/src/mpack.c
mpack/mpack-src/src/object.c
mpack/mpack-src/src/object.h
mpack/mpack-src/src/rpc.c
mpack/mpack-src/src/rpc.h
mpack/mpack-src/test/fixtures.c
mpack/mpack-src/test/fixtures.h
mpack/mpack-src/test/mpack.c
mpack/mpack-src/test/tap.h
mpack/mpack-src/test/deps/tap/tap.c
mpack/mpack-src/test/deps/tap/tap.h